<?xml version="1.0"?>
<xml>
<!-- used in index.php for displaying webcam tag, modified in settings.php -->
<DisplayWebcam>0</DisplayWebcam><!-- 1 = on ; 0 = off -->
<SkinChooseByUser>default</SkinChooseByUser>
<SkinList>
	<skin>default</skin>
	<skin>dragon</skin>
	<skin>bitecoin</skin>
	<skin>blackskin</skin>
	<skin>fractalDemonix</skin>
	<skin>freedom</skin>
	<skin>gold</skin>
</SkinList>
<trade>
	<euro>0.00</euro>
	<euro_last>0.00</euro_last>
	<dollars>0.00</dollars>
	<dollars_last>0.00</dollars_last>
	<update>1</update>
</trade>
<LangList><!-- //TODO: full locale support http://userguide.icu-project.org/locale -->
	<fr>Fran&#xE7;ais</fr>
	<en>English</en>
	<no>norsk</no>
</LangList>
<LangChoosed>en</LangChoosed>
</xml>
